py_jaeger_tracing/__init__.py
py_jaeger_tracing/extractors/__init__.py
py_jaeger_tracing/extractors/dictionary.py
py_jaeger_tracing/extractors/string.py
py_jaeger_tracing/global_variables.py
py_jaeger_tracing/injectors/__init__.py
py_jaeger_tracing/injectors/dictionary.py
py_jaeger_tracing/injectors/string.py
py_jaeger_tracing/logger/__init__.py
py_jaeger_tracing/logger/handler.py
py_jaeger_tracing/main.py
py_jaeger_tracing/mixin/__init__.py
py_jaeger_tracing/mixin/tornado.py
py_jaeger_tracing/patches/__init__.py
py_jaeger_tracing/patches/boto3.py
py_jaeger_tracing/patches/patches.py
py_jaeger_tracing/patches/requests.py
py_jaeger_tracing/shutdown.py
py_jaeger_tracing/utils/__init__.py
py_jaeger_tracing/utils/context.py
py_jaeger_tracing/utils/decorator.py
py_jaeger_tracing/utils/event_loop.py
py_jaeger_tracing-1.1.9.dist-info/LICENSE
py_jaeger_tracing-1.1.9.dist-info/WHEEL
py_jaeger_tracing-1.1.9.dist-info/METADATA
py_jaeger_tracing-1.1.9.dist-info/RECORD
